algokit_utils/__init__.py
algokit_utils/_debugging.py
algokit_utils/_legacy_v2/__init__.py
algokit_utils/_legacy_v2/_ensure_funded.py
algokit_utils/_legacy_v2/_transfer.py
algokit_utils/_legacy_v2/account.py
algokit_utils/_legacy_v2/application_client.py
algokit_utils/_legacy_v2/application_specification.py
algokit_utils/_legacy_v2/asset.py
algokit_utils/_legacy_v2/common.py
algokit_utils/_legacy_v2/deploy.py
algokit_utils/_legacy_v2/logic_error.py
algokit_utils/_legacy_v2/models.py
algokit_utils/_legacy_v2/network_clients.py
algokit_utils/account.py
algokit_utils/accounts/__init__.py
algokit_utils/accounts/account_manager.py
algokit_utils/accounts/kmd_account_manager.py
algokit_utils/algorand.py
algokit_utils/application_client.py
algokit_utils/application_specification.py
algokit_utils/applications/__init__.py
algokit_utils/applications/abi.py
algokit_utils/applications/app_client.py
algokit_utils/applications/app_deployer.py
algokit_utils/applications/app_factory.py
algokit_utils/applications/app_manager.py
algokit_utils/applications/app_spec/__init__.py
algokit_utils/applications/app_spec/arc32.py
algokit_utils/applications/app_spec/arc56.py
algokit_utils/applications/enums.py
algokit_utils/asset.py
algokit_utils/assets/__init__.py
algokit_utils/assets/asset_manager.py
algokit_utils/beta/_utils.py
algokit_utils/beta/account_manager.py
algokit_utils/beta/algorand_client.py
algokit_utils/beta/client_manager.py
algokit_utils/beta/composer.py
algokit_utils/clients/__init__.py
algokit_utils/clients/client_manager.py
algokit_utils/clients/dispenser_api_client.py
algokit_utils/common.py
algokit_utils/config.py
algokit_utils/deploy.py
algokit_utils/dispenser_api.py
algokit_utils/errors/__init__.py
algokit_utils/errors/logic_error.py
algokit_utils/logic_error.py
algokit_utils/models/__init__.py
algokit_utils/models/account.py
algokit_utils/models/amount.py
algokit_utils/models/application.py
algokit_utils/models/network.py
algokit_utils/models/simulate.py
algokit_utils-4.2.2.dist-info/METADATA
algokit_utils-4.2.2.dist-info/WHEEL
algokit_utils-4.2.2.dist-info/licenses/LICENSE
algokit_utils-4.2.2.dist-info/RECORD
