Metadata-Version: 2.4
Name: algokit-utils
Version: 4.2.2
Summary: Utilities for Algorand development for use by AlgoKit
License: MIT
License-File: LICENSE
Author: Algorand Foundation
Author-email: contact@algorand.foundation
Requires-Python: >=3.10,<4.0
Classifier: License :: OSI Approved :: MIT License
Classifier: Programming Language :: Python :: 3
Classifier: Programming Language :: Python :: 3.10
Classifier: Programming Language :: Python :: 3.11
Classifier: Programming Language :: Python :: 3.12
Classifier: Programming Language :: Python :: 3.13
Classifier: Programming Language :: Python :: 3.14
Requires-Dist: httpx (>=0.23.1,<=0.28.1)
Requires-Dist: py-algorand-sdk (>=2.11.0,<3.0.0)
Requires-Dist: typing-extensions (>=4.6.0)
